bayesn/__init__.py
bayesn/bayesn_io.py
bayesn/bayesn_model.py
bayesn/spline_utils.py
bayesn/zltn_utils.py
bayesn/bayesn-filters/filters.yaml
bayesn/bayesn-filters/filters/CTIO/ANDICAM/Bandicam.dat
bayesn/bayesn-filters/filters/CTIO/ANDICAM/H_andi.txt
bayesn/bayesn-filters/filters/CTIO/ANDICAM/Handicam.dat
bayesn/bayesn-filters/filters/CTIO/ANDICAM/Iandicam.dat
bayesn/bayesn-filters/filters/CTIO/ANDICAM/J_andi.txt
bayesn/bayesn-filters/filters/CTIO/ANDICAM/Jandicam.dat
bayesn/bayesn-filters/filters/CTIO/ANDICAM/Kandicam.dat
bayesn/bayesn-filters/filters/CTIO/ANDICAM/README
bayesn/bayesn-filters/filters/CTIO/ANDICAM/Randicam.dat
bayesn/bayesn-filters/filters/CTIO/ANDICAM/Vandicam.dat
bayesn/bayesn-filters/filters/CTIO/ANDICAM/Yandicam.dat
bayesn/bayesn-filters/filters/CTIO/ANDICAM/filters.dat
bayesn/bayesn-filters/filters/DECam/decam_g.txt
bayesn/bayesn-filters/filters/DECam/decam_i.txt
bayesn/bayesn-filters/filters/DECam/decam_r.txt
bayesn/bayesn-filters/filters/DECam/decam_u.txt
bayesn/bayesn-filters/filters/DECam/decam_y.txt
bayesn/bayesn-filters/filters/DECam/decam_z.txt
bayesn/bayesn-filters/filters/HST/WFC3/filters.dat
bayesn/bayesn-filters/filters/HST/WFC3/wfc3_ir_f160w.dat
bayesn/bayesn-filters/filters/HST/WFC3/IR/F105W.dat
bayesn/bayesn-filters/filters/HST/WFC3/IR/F125W.dat
bayesn/bayesn-filters/filters/HST/WFC3/IR/F140W.dat
bayesn/bayesn-filters/filters/HST/WFC3/IR/F160W.dat
bayesn/bayesn-filters/filters/HST/WFC3/UVIS2/F225W.dat
bayesn/bayesn-filters/filters/HST/WFC3/UVIS2/F275W.dat
bayesn/bayesn-filters/filters/HST/WFC3/UVIS2/F300X.dat
bayesn/bayesn-filters/filters/HST/WFC3/UVIS2/F336W.dat
bayesn/bayesn-filters/filters/HST/WFC3/UVIS2/F390W.dat
bayesn/bayesn-filters/filters/HST/WFC3/UVIS2/F438W.dat
bayesn/bayesn-filters/filters/HST/WFC3/UVIS2/F475W.dat
bayesn/bayesn-filters/filters/HST/WFC3/UVIS2/F555W.dat
bayesn/bayesn-filters/filters/HST/WFC3/UVIS2/F625W.dat
bayesn/bayesn-filters/filters/HST/WFC3/UVIS2/F814W.dat
bayesn-0.4.0.dist-info/LICENSE
bayesn-0.4.0.dist-info/METADATA
bayesn-0.4.0.dist-info/WHEEL
bayesn-0.4.0.dist-info/top_level.txt
bayesn-0.4.0.dist-info/RECORD
