Metadata-Version: 2.1
Name: bayesn
Version: 0.4.0
Summary: Hierarchical Bayesian modelling of type Ia SNe
Home-page: https://github.com/bayesn/bayesn
Author: Matt Grayling, Stephen Thorp, Kaisey Mandel
Author-email: mg2102@cam.ac.uk
Requires-Python: >=3.10
License-File: LICENSE
Requires-Dist: numpy
Requires-Dist: pandas
Requires-Dist: matplotlib
Requires-Dist: h5py
Requires-Dist: sncosmo
Requires-Dist: arviz
Requires-Dist: astropy
Requires-Dist: extinction
Requires-Dist: jax
Requires-Dist: numpyro
Requires-Dist: scipy
Requires-Dist: ruamel.yaml
Requires-Dist: tqdm
Provides-Extra: docs
Requires-Dist: numpy ; extra == 'docs'
Requires-Dist: sphinx ; extra == 'docs'
Requires-Dist: sphinx-rtd-theme ; extra == 'docs'
Requires-Dist: pillow ; extra == 'docs'
Requires-Dist: numpydoc ; extra == 'docs'
